ktb_format/__init__.py
ktb_format/ktb_class.py
ktb_format/ktb_mtx.py
ktb_format-0.0.5.dist-info/METADATA
ktb_format-0.0.5.dist-info/WHEEL
ktb_format-0.0.5.dist-info/top_level.txt
ktb_format-0.0.5.dist-info/RECORD
